[
  {
    "rewards": {
      "decimals": 9,
      "tradeRewardNumerator": 1,
      "tradeRewardDenominator": 1000,
      "tradeRewardCap": 100000000
    },
    "farmRewards": {
      "aprNumerator": 1,
      "aprDenominator": 500
    },
    "symbol": "USDC"
  },
  {
    "farmRewards": {
      "aprNumerator": 1,
      "aprDenominator": 500
    },
    "rewards": {
      "decimals": 9,
      "tradeRewardNumerator": 1,
      "tradeRewardDenominator": 1000,
      "tradeRewardCap": 100000000
    },
    "symbol": "USDT"
  },
  {
    "rewards": {
      "decimals": 9,
      "tradeRewardNumerator": 1,
      "tradeRewardDenominator": 1000000,
      "tradeRewardCap": 100000000
    },
    "farmRewards": {
      "aprNumerator": 1,
      "aprDenominator": 500
    },
    "symbol": "SOL"
  },
  {
    "rewards": {
      "decimals": 9,
      "tradeRewardNumerator": 1,
      "tradeRewardDenominator": 1000,
      "tradeRewardCap": 100000000
    },
    "farmRewards": {
      "aprNumerator": 1,
      "aprDenominator": 500
    },
    "symbol": "SRM"
  }
]
